{
  "data": [
    {
      "items": "1",
      "er": "0",
      "course": "559",
      "group": "3777",
      "unity": "569",
      "lesson": "596",
      "acpro": "3184",
      "typepro": "20",
      "pos": 0,
      "tini": "2025-04-20 07:59:48",
      "tlesson": "2025-04-20 08:03:53",
      "keyin": "",
      "activity": "13089",
      "session_id": "",
      "typeOption": "save_multiple_progress"
    },
    {
      "items": "3",
      "er": "0",
      "course": "559",
      "group": "3777",
      "unity": "569",
      "lesson": "596",
      "acpro": "460",
      "typepro": "9",
      "pos": 0,
      "tini": "2025-04-20 07:59:48",
      "tlesson": "2025-04-20 08:03:53",
      "keyin": "",
      "activity": "13042",
      "session_id": "",
      "typeOption": "save_multiple_progress"
    },
    {
      "items": "4",
      "er": "0",
      "course": "559",
      "group": "3777",
      "unity": "569",
      "lesson": "596",
      "acpro": "1937",
      "typepro": "9",
      "pos": 0,
      "tini": "2025-04-20 07:59:48",
      "tlesson": "2025-04-20 08:03:53",
      "keyin": "",
      "activity": "13061",
      "session_id": "",
      "typeOption": "save_multiple_progress"
    },
    {
      "items": "4",
      "er": "0",
      "course": "559",
      "group": "3777",
      "unity": "569",
      "lesson": "596",
      "acpro": "306",
      "typepro": "9",
      "pos": 0,
      "tini": "2025-04-20 07:59:48",
      "tlesson": "2025-04-20 08:03:53",
      "keyin": "",
      "activity": "13057",
      "session_id": "",
      "typeOption": "save_multiple_progress"
    },
    {
      "items": "4",
      "er": "0",
      "course": "559",
      "group": "3777",
      "unity": "569",
      "lesson": "596",
      "acpro": "1938",
      "typepro": "9",
      "pos": 0,
      "tini": "2025-04-20 07:59:48",
      "tlesson": "2025-04-20 08:03:53",
      "keyin": "",
      "activity": "13064",
      "session_id": "",
      "typeOption": "save_multiple_progress"
    },
    {
      "items": "4",
      "er": "0",
      "course": "559",
      "group": "3777",
      "unity": "569",
      "lesson": "596",
      "acpro": "1940",
      "typepro": "9",
      "pos": 0,
      "tini": "2025-04-20 07:59:48",
      "tlesson": "2025-04-20 08:03:53",
      "keyin": "",
      "activity": "13068",
      "session_id": "",
      "typeOption": "save_multiple_progress"
    },
    {
      "items": "4",
      "er": "0",
      "course": "559",
      "group": "3777",
      "unity": "569",
      "lesson": "596",
      "acpro": "314",
      "typepro": "9",
      "pos": 0,
      "tini": "2025-04-20 07:59:48",
      "tlesson": "2025-04-20 08:03:53",
      "keyin": "",
      "activity": "13046",
      "session_id": "",
      "typeOption": "save_multiple_progress"
    },
    {
      "items": "4",
      "er": "0",
      "course": "559",
      "group": "3777",
      "unity": "569",
      "lesson": "596",
      "acpro": "312",
      "typepro": "9",
      "pos": 0,
      "tini": "2025-04-20 07:59:48",
      "tlesson": "2025-04-20 08:03:53",
      "keyin": "",
      "activity": "13050",
      "session_id": "",
      "typeOption": "save_multiple_progress"
    },
    {
      "items": "4",
      "er": "0",
      "course": "559",
      "group": "3777",
      "unity": "569",
      "lesson": "596",
      "acpro": "309",
      "typepro": "9",
      "pos": 0,
      "tini": "2025-04-20 07:59:48",
      "tlesson": "2025-04-20 08:03:53",
      "keyin": "",
      "activity": "13054",
      "session_id": "",
      "typeOption": "save_multiple_progress"
    },
    {
      "items": "4",
      "er": "0",
      "course": "559",
      "group": "3777",
      "unity": "569",
      "lesson": "596",
      "acpro": "306",
      "typepro": "10",
      "pos": 0,
      "tini": "2025-04-20 07:59:48",
      "tlesson": "2025-04-20 08:03:53",
      "keyin": "",
      "activity": "13058",
      "session_id": "",
      "typeOption": "save_multiple_progress"
    },
    {
      "items": "3",
      "er": "0",
      "course": "559",
      "group": "3777",
      "unity": "569",
      "lesson": "596",
      "acpro": "460",
      "typepro": "10",
      "pos": 0,
      "tini": "2025-04-20 07:59:48",
      "tlesson": "2025-04-20 08:03:53",
      "keyin": "",
      "activity": "13043",
      "session_id": "",
      "typeOption": "save_multiple_progress"
    },
    {
      "items": "4",
      "er": "0",
      "course": "559",
      "group": "3777",
      "unity": "569",
      "lesson": "596",
      "acpro": "1943",
      "typepro": "10",
      "pos": 0,
      "tini": "2025-04-20 07:59:48",
      "tlesson": "2025-04-20 08:03:53",
      "keyin": "",
      "activity": "13072",
      "session_id": "",
      "typeOption": "save_multiple_progress"
    },
    {
      "items": "4",
      "er": "0",
      "course": "559",
      "group": "3777",
      "unity": "569",
      "lesson": "596",
      "acpro": "1944",
      "typepro": "10",
      "pos": 0,
      "tini": "2025-04-20 07:59:48",
      "tlesson": "2025-04-20 08:03:53",
      "keyin": "",
      "activity": "13076",
      "session_id": "",
      "typeOption": "save_multiple_progress"
    },
    {
      "items": "3",
      "er": "0",
      "course": "559",
      "group": "3777",
      "unity": "569",
      "lesson": "596",
      "acpro": "460",
      "typepro": "19",
      "pos": 0,
      "tini": "2025-04-20 07:59:48",
      "tlesson": "2025-04-20 08:03:53",
      "keyin": "",
      "activity": "13045",
      "session_id": "",
      "typeOption": "save_multiple_progress"
    },
    {
      "items": "3",
      "er": "0",
      "course": "559",
      "group": "3777",
      "unity": "569",
      "lesson": "596",
      "acpro": "460",
      "typepro": "18",
      "pos": 0,
      "tini": "2025-04-20 07:59:48",
      "tlesson": "2025-04-20 08:03:53",
      "keyin": "",
      "activity": "13044",
      "session_id": "",
      "typeOption": "save_multiple_progress"
    },
    {
      "items": "4",
      "er": "0",
      "course": "559",
      "group": "3777",
      "unity": "569",
      "lesson": "596",
      "acpro": "306",
      "typepro": "19",
      "pos": 0,
      "tini": "2025-04-20 07:59:48",
      "tlesson": "2025-04-20 08:03:53",
      "keyin": "",
      "activity": "13060",
      "session_id": "",
      "typeOption": "save_multiple_progress"
    },
    {
      "items": "4",
      "er": "0",
      "course": "559",
      "group": "3777",
      "unity": "569",
      "lesson": "596",
      "acpro": "1938",
      "typepro": "21",
      "pos": 0,
      "tini": "2025-04-20 07:59:48",
      "tlesson": "2025-04-20 08:03:53",
      "keyin": "",
      "activity": "13067",
      "session_id": "",
      "typeOption": "save_multiple_progress"
    },
    {
      "items": "4",
      "er": "0",
      "course": "559",
      "group": "3777",
      "unity": "569",
      "lesson": "596",
      "acpro": "1940",
      "typepro": "21",
      "pos": 0,
      "tini": "2025-04-20 07:59:48",
      "tlesson": "2025-04-20 08:03:53",
      "keyin": "",
      "activity": "13071",
      "session_id": "",
      "typeOption": "save_multiple_progress"
    },
    {
      "items": "4",
      "er": "0",
      "course": "559",
      "group": "3777",
      "unity": "569",
      "lesson": "596",
      "acpro": "1943",
      "typepro": "21",
      "pos": 0,
      "tini": "2025-04-20 07:59:48",
      "tlesson": "2025-04-20 08:03:53",
      "keyin": "",
      "activity": "13075",
      "session_id": "",
      "typeOption": "save_multiple_progress"
    },
    {
      "items": "4",
      "er": "0",
      "course": "559",
      "group": "3777",
      "unity": "569",
      "lesson": "596",
      "acpro": "312",
      "typepro": "18",
      "pos": 0,
      "tini": "2025-04-20 07:59:48",
      "tlesson": "2025-04-20 08:03:53",
      "keyin": "",
      "activity": "13053",
      "session_id": "",
      "typeOption": "save_multiple_progress"
    },
    {
      "items": "4",
      "er": "0",
      "course": "559",
      "group": "3777",
      "unity": "569",
      "lesson": "596",
      "acpro": "1944",
      "typepro": "21",
      "pos": 0,
      "tini": "2025-04-20 07:59:48",
      "tlesson": "2025-04-20 08:03:53",
      "keyin": "",
      "activity": "13079",
      "session_id": "",
      "typeOption": "save_multiple_progress"
    },
    {
      "items": "4",
      "er": "0",
      "course": "559",
      "group": "3777",
      "unity": "569",
      "lesson": "596",
      "acpro": "314",
      "typepro": "21",
      "pos": 0,
      "tini": "2025-04-20 07:59:48",
      "tlesson": "2025-04-20 08:03:53",
      "keyin": "",
      "activity": "13049",
      "session_id": "",
      "typeOption": "save_multiple_progress"
    },
    {
      "items": "4",
      "er": "0",
      "course": "559",
      "group": "3777",
      "unity": "569",
      "lesson": "596",
      "acpro": "309",
      "typepro": "18",
      "pos": 0,
      "tini": "2025-04-20 07:59:48",
      "tlesson": "2025-04-20 08:03:53",
      "keyin": "",
      "activity": "13056",
      "session_id": "",
      "typeOption": "save_multiple_progress"
    },
    {
      "items": "4",
      "er": "0",
      "course": "559",
      "group": "3777",
      "unity": "569",
      "lesson": "596",
      "acpro": "1944",
      "typepro": "14",
      "pos": 0,
      "tini": "2025-04-20 07:59:48",
      "tlesson": "2025-04-20 08:03:53",
      "keyin": "",
      "activity": "13077",
      "session_id": "",
      "typeOption": "save_multiple_progress"
    },
    {
      "items": "4",
      "er": "0",
      "course": "559",
      "group": "3777",
      "unity": "569",
      "lesson": "596",
      "acpro": "1943",
      "typepro": "14",
      "pos": 0,
      "tini": "2025-04-20 07:59:48",
      "tlesson": "2025-04-20 08:03:53",
      "keyin": "",
      "activity": "13073",
      "session_id": "",
      "typeOption": "save_multiple_progress"
    },
    {
      "items": "4",
      "er": "0",
      "course": "559",
      "group": "3777",
      "unity": "569",
      "lesson": "596",
      "acpro": "1940",
      "typepro": "14",
      "pos": 0,
      "tini": "2025-04-20 07:59:48",
      "tlesson": "2025-04-20 08:03:53",
      "keyin": "",
      "activity": "13069",
      "session_id": "",
      "typeOption": "save_multiple_progress"
    },
    {
      "items": "4",
      "er": "0",
      "course": "559",
      "group": "3777",
      "unity": "569",
      "lesson": "596",
      "acpro": "312",
      "typepro": "14",
      "pos": 0,
      "tini": "2025-04-20 07:59:48",
      "tlesson": "2025-04-20 08:03:53",
      "keyin": "",
      "activity": "13051",
      "session_id": "",
      "typeOption": "save_multiple_progress"
    },
    {
      "items": "4",
      "er": "0",
      "course": "559",
      "group": "3777",
      "unity": "569",
      "lesson": "596",
      "acpro": "314",
      "typepro": "14",
      "pos": 0,
      "tini": "2025-04-20 07:59:48",
      "tlesson": "2025-04-20 08:03:53",
      "keyin": "",
      "activity": "13047",
      "session_id": "",
      "typeOption": "save_multiple_progress"
    },
    {
      "items": "4",
      "er": "0",
      "course": "559",
      "group": "3777",
      "unity": "569",
      "lesson": "596",
      "acpro": "1938",
      "typepro": "14",
      "pos": 0,
      "tini": "2025-04-20 07:59:48",
      "tlesson": "2025-04-20 08:03:53",
      "keyin": "",
      "activity": "13065",
      "session_id": "",
      "typeOption": "save_multiple_progress"
    },
    {
      "items": "4",
      "er": "0",
      "course": "559",
      "group": "3777",
      "unity": "569",
      "lesson": "596",
      "acpro": "306",
      "typepro": "14",
      "pos": 0,
      "tini": "2025-04-20 07:59:48",
      "tlesson": "2025-04-20 08:03:53",
      "keyin": "",
      "activity": "13059",
      "session_id": "",
      "typeOption": "save_multiple_progress"
    },
    {
      "items": "4",
      "er": "0",
      "course": "559",
      "group": "3777",
      "unity": "569",
      "lesson": "596",
      "acpro": "1937",
      "typepro": "14",
      "pos": 0,
      "tini": "2025-04-20 07:59:48",
      "tlesson": "2025-04-20 08:03:53",
      "keyin": "",
      "activity": "13062",
      "session_id": "",
      "typeOption": "save_multiple_progress"
    },
    {
      "items": "4",
      "er": "0",
      "course": "559",
      "group": "3777",
      "unity": "569",
      "lesson": "596",
      "acpro": "1937",
      "typepro": "15",
      "pos": 0,
      "tini": "2025-04-20 07:59:48",
      "tlesson": "2025-04-20 08:03:53",
      "keyin": "",
      "activity": "13063",
      "session_id": "",
      "typeOption": "save_multiple_progress"
    },
    {
      "items": "4",
      "er": "0",
      "course": "559",
      "group": "3777",
      "unity": "569",
      "lesson": "596",
      "acpro": "1938",
      "typepro": "15",
      "pos": 0,
      "tini": "2025-04-20 07:59:48",
      "tlesson": "2025-04-20 08:03:53",
      "keyin": "",
      "activity": "13066",
      "session_id": "",
      "typeOption": "save_multiple_progress"
    },
    {
      "items": "4",
      "er": "0",
      "course": "559",
      "group": "3777",
      "unity": "569",
      "lesson": "596",
      "acpro": "1943",
      "typepro": "15",
      "pos": 0,
      "tini": "2025-04-20 07:59:48",
      "tlesson": "2025-04-20 08:03:53",
      "keyin": "",
      "activity": "13074",
      "session_id": "",
      "typeOption": "save_multiple_progress"
    },
    {
      "items": "4",
      "er": "0",
      "course": "559",
      "group": "3777",
      "unity": "569",
      "lesson": "596",
      "acpro": "1940",
      "typepro": "15",
      "pos": 0,
      "tini": "2025-04-20 07:59:48",
      "tlesson": "2025-04-20 08:03:53",
      "keyin": "",
      "activity": "13070",
      "session_id": "",
      "typeOption": "save_multiple_progress"
    },
    {
      "items": "4",
      "er": "0",
      "course": "559",
      "group": "3777",
      "unity": "569",
      "lesson": "596",
      "acpro": "314",
      "typepro": "15",
      "pos": 0,
      "tini": "2025-04-20 07:59:48",
      "tlesson": "2025-04-20 08:03:53",
      "keyin": "",
      "activity": "13048",
      "session_id": "",
      "typeOption": "save_multiple_progress"
    },
    {
      "items": "4",
      "er": "0",
      "course": "559",
      "group": "3777",
      "unity": "569",
      "lesson": "596",
      "acpro": "312",
      "typepro": "15",
      "pos": 0,
      "tini": "2025-04-20 07:59:48",
      "tlesson": "2025-04-20 08:03:53",
      "keyin": "",
      "activity": "13052",
      "session_id": "",
      "typeOption": "save_multiple_progress"
    },
    {
      "items": "4",
      "er": "0",
      "course": "559",
      "group": "3777",
      "unity": "569",
      "lesson": "596",
      "acpro": "1944",
      "typepro": "15",
      "pos": 0,
      "tini": "2025-04-20 07:59:48",
      "tlesson": "2025-04-20 08:03:53",
      "keyin": "",
      "activity": "13078",
      "session_id": "",
      "typeOption": "save_multiple_progress"
    },
    {
      "items": "4",
      "er": "0",
      "course": "559",
      "group": "3777",
      "unity": "569",
      "lesson": "596",
      "acpro": "309",
      "typepro": "15",
      "pos": 0,
      "tini": "2025-04-20 07:59:48",
      "tlesson": "2025-04-20 08:03:53",
      "keyin": "",
      "activity": "13055",
      "session_id": "",
      "typeOption": "save_multiple_progress"
    },
    {
      "items": "4",
      "er": "0",
      "course": "559",
      "group": "3777",
      "unity": "569",
      "lesson": "596",
      "acpro": "1902",
      "typepro": "20",
      "pos": 0,
      "tini": "2025-04-20 07:59:48",
      "tlesson": "2025-04-20 08:03:53",
      "keyin": "",
      "activity": "13081",
      "session_id": "",
      "typeOption": "save_multiple_progress"
    },
    {
      "items": "14",
      "er": "0",
      "course": "559",
      "group": "3777",
      "unity": "569",
      "lesson": "596",
      "acpro": "455",
      "typepro": "16",
      "pos": 0,
      "tini": "2025-04-20 07:59:48",
      "tlesson": "2025-04-20 08:03:53",
      "keyin": "",
      "activity": "13093",
      "session_id": "",
      "typeOption": "save_multiple_progress"
    },
    {
      "items": "2",
      "er": "0",
      "course": "559",
      "group": "3777",
      "unity": "569",
      "lesson": "596",
      "acpro": "1912",
      "typepro": "20",
      "pos": 0,
      "tini": "2025-04-20 07:59:48",
      "tlesson": "2025-04-20 08:03:53",
      "keyin": "",
      "activity": "13084",
      "session_id": "",
      "typeOption": "save_multiple_progress"
    },
    {
      "items": "2",
      "er": "0",
      "course": "559",
      "group": "3777",
      "unity": "569",
      "lesson": "596",
      "acpro": "1913",
      "typepro": "20",
      "pos": 0,
      "tini": "2025-04-20 07:59:48",
      "tlesson": "2025-04-20 08:03:53",
      "keyin": "",
      "activity": "13085",
      "session_id": "",
      "typeOption": "save_multiple_progress"
    },
    {
      "items": "3",
      "er": "0",
      "course": "559",
      "group": "3777",
      "unity": "569",
      "lesson": "596",
      "acpro": "315",
      "typepro": "20",
      "pos": 0,
      "tini": "2025-04-20 07:59:48",
      "tlesson": "2025-04-20 08:03:53",
      "keyin": "",
      "activity": "13091",
      "session_id": "",
      "typeOption": "save_multiple_progress"
    },
    {
      "items": "4",
      "er": "0",
      "course": "559",
      "group": "3777",
      "unity": "569",
      "lesson": "596",
      "acpro": "1921",
      "typepro": "20",
      "pos": 0,
      "tini": "2025-04-20 07:59:48",
      "tlesson": "2025-04-20 08:03:53",
      "keyin": "",
      "activity": "13092",
      "session_id": "",
      "typeOption": "save_multiple_progress"
    },
    {
      "items": "2",
      "er": "0",
      "course": "559",
      "group": "3777",
      "unity": "569",
      "lesson": "596",
      "acpro": "1914",
      "typepro": "20",
      "pos": 0,
      "tini": "2025-04-20 07:59:48",
      "tlesson": "2025-04-20 08:03:53",
      "keyin": "",
      "activity": "13087",
      "session_id": "",
      "typeOption": "save_multiple_progress"
    },
    {
      "items": "2",
      "er": "0",
      "course": "559",
      "group": "3777",
      "unity": "569",
      "lesson": "596",
      "acpro": "1908",
      "typepro": "20",
      "pos": 0,
      "tini": "2025-04-20 07:59:48",
      "tlesson": "2025-04-20 08:03:53",
      "keyin": "",
      "activity": "13086",
      "session_id": "",
      "typeOption": "save_multiple_progress"
    },
    {
      "items": "2",
      "er": "0",
      "course": "559",
      "group": "3777",
      "unity": "569",
      "lesson": "596",
      "acpro": "1910",
      "typepro": "20",
      "pos": 0,
      "tini": "2025-04-20 07:59:48",
      "tlesson": "2025-04-20 08:03:53",
      "keyin": "",
      "activity": "13083",
      "session_id": "",
      "typeOption": "save_multiple_progress"
    },
    {
      "items": "2",
      "er": "0",
      "course": "559",
      "group": "3777",
      "unity": "569",
      "lesson": "596",
      "acpro": "1909",
      "typepro": "20",
      "pos": 0,
      "tini": "2025-04-20 07:59:48",
      "tlesson": "2025-04-20 08:03:53",
      "keyin": "",
      "activity": "13082",
      "session_id": "",
      "typeOption": "save_multiple_progress"
    }
  ],
  "dataV2": {
    "group": "3777",
    "course": "559",
    "unity": "569",
    "lesson": "596",
    "array_activitys": [
      {
        "total": "1",
        "errors": 0,
        "success": "1",
        "type": "20",
        "activity": "13089"
      },
      {
        "total": "3",
        "errors": 0,
        "success": "3",
        "type": "9",
        "activity": "13042"
      },
      {
        "total": "4",
        "errors": 0,
        "success": "4",
        "type": "9",
        "activity": "13061"
      },
      {
        "total": "4",
        "errors": 0,
        "success": "4",
        "type": "9",
        "activity": "13057"
      },
      {
        "total": "4",
        "errors": 0,
        "success": "4",
        "type": "9",
        "activity": "13064"
      },
      {
        "total": "4",
        "errors": 0,
        "success": "4",
        "type": "9",
        "activity": "13068"
      },
      {
        "total": "4",
        "errors": 0,
        "success": "4",
        "type": "9",
        "activity": "13046"
      },
      {
        "total": "4",
        "errors": 0,
        "success": "4",
        "type": "9",
        "activity": "13050"
      },
      {
        "total": "4",
        "errors": 0,
        "success": "4",
        "type": "9",
        "activity": "13054"
      },
      {
        "total": "4",
        "errors": 0,
        "success": "4",
        "type": "10",
        "activity": "13058"
      },
      {
        "total": "3",
        "errors": 0,
        "success": "3",
        "type": "10",
        "activity": "13043"
      },
      {
        "total": "4",
        "errors": 0,
        "success": "4",
        "type": "10",
        "activity": "13072"
      },
      {
        "total": "4",
        "errors": 0,
        "success": "4",
        "type": "10",
        "activity": "13076"
      },
      {
        "total": "3",
        "errors": 0,
        "success": "3",
        "type": "19",
        "activity": "13045"
      },
      {
        "total": "3",
        "errors": 0,
        "success": "3",
        "type": "18",
        "activity": "13044"
      },
      {
        "total": "4",
        "errors": 0,
        "success": "4",
        "type": "19",
        "activity": "13060"
      },
      {
        "total": "4",
        "errors": 0,
        "success": "4",
        "type": "21",
        "activity": "13067"
      },
      {
        "total": "4",
        "errors": 0,
        "success": "4",
        "type": "21",
        "activity": "13071"
      },
      {
        "total": "4",
        "errors": 0,
        "success": "4",
        "type": "21",
        "activity": "13075"
      },
      {
        "total": "4",
        "errors": 0,
        "success": "4",
        "type": "18",
        "activity": "13053"
      },
      {
        "total": "4",
        "errors": 0,
        "success": "4",
        "type": "21",
        "activity": "13079"
      },
      {
        "total": "4",
        "errors": 0,
        "success": "4",
        "type": "21",
        "activity": "13049"
      },
      {
        "total": "4",
        "errors": 0,
        "success": "4",
        "type": "18",
        "activity": "13056"
      },
      {
        "total": "4",
        "errors": 0,
        "success": "4",
        "type": "14",
        "activity": "13077"
      },
      {
        "total": "4",
        "errors": 0,
        "success": "4",
        "type": "14",
        "activity": "13073"
      },
      {
        "total": "4",
        "errors": 0,
        "success": "4",
        "type": "14",
        "activity": "13069"
      },
      {
        "total": "4",
        "errors": 0,
        "success": "4",
        "type": "14",
        "activity": "13051"
      },
      {
        "total": "4",
        "errors": 0,
        "success": "4",
        "type": "14",
        "activity": "13047"
      },
      {
        "total": "4",
        "errors": 0,
        "success": "4",
        "type": "14",
        "activity": "13065"
      },
      {
        "total": "4",
        "errors": 0,
        "success": "4",
        "type": "14",
        "activity": "13059"
      },
      {
        "total": "4",
        "errors": 0,
        "success": "4",
        "type": "14",
        "activity": "13062"
      },
      {
        "total": "4",
        "errors": 0,
        "success": "4",
        "type": "15",
        "activity": "13063"
      },
      {
        "total": "4",
        "errors": 0,
        "success": "4",
        "type": "15",
        "activity": "13066"
      },
      {
        "total": "4",
        "errors": 0,
        "success": "4",
        "type": "15",
        "activity": "13074"
      },
      {
        "total": "4",
        "errors": 0,
        "success": "4",
        "type": "15",
        "activity": "13070"
      },
      {
        "total": "4",
        "errors": 0,
        "success": "4",
        "type": "15",
        "activity": "13048"
      },
      {
        "total": "4",
        "errors": 0,
        "success": "4",
        "type": "15",
        "activity": "13052"
      },
      {
        "total": "4",
        "errors": 0,
        "success": "4",
        "type": "15",
        "activity": "13078"
      },
      {
        "total": "4",
        "errors": 0,
        "success": "4",
        "type": "15",
        "activity": "13055"
      },
      {
        "total": "4",
        "errors": 0,
        "success": "4",
        "type": "20",
        "activity": "13081"
      },
      {
        "total": "14",
        "errors": 0,
        "success": "14",
        "type": "16",
        "activity": "13093"
      },
      {
        "total": "2",
        "errors": 0,
        "success": "2",
        "type": "20",
        "activity": "13084"
      },
      {
        "total": "2",
        "errors": 0,
        "success": "2",
        "type": "20",
        "activity": "13085"
      },
      {
        "total": "3",
        "errors": 0,
        "success": "3",
        "type": "20",
        "activity": "13091"
      },
      {
        "total": "4",
        "errors": 0,
        "success": "4",
        "type": "20",
        "activity": "13092"
      },
      {
        "total": "2",
        "errors": 0,
        "success": "2",
        "type": "20",
        "activity": "13087"
      },
      {
        "total": "2",
        "errors": 0,
        "success": "2",
        "type": "20",
        "activity": "13086"
      },
      {
        "total": "2",
        "errors": 0,
        "success": "2",
        "type": "20",
        "activity": "13083"
      },
      {
        "total": "2",
        "errors": 0,
        "success": "2",
        "type": "20",
        "activity": "13082"
      }
    ],
    "total_activitys": 185,
    "errors_result_activitys": 0,
    "success_result_activitys": 185,
    "pending_result_activitys": 0,
    "total_groups_activitys": 49,
    "total_groups_activitys_success": 49,
    "total_groups_activitys_pendings": 0,
    "success_lesson_date": "",
    "success_lesson_activities": 2,
    "year": "2025"
  },
  "typeOption": "save_multiple_progress_webv2"
}