{
  "data": [
    {
      "items": "4",
      "er": "0",
      "course": "573",
      "group": "3869",
      "unity": "579",
      "lesson": "630",
      "acpro": "2538",
      "typepro": "14",
      "pos": 0,
      "tini": "2025-04-20 07:59:48",
      "tlesson": "2025-04-20 08:03:53",
      "keyin": "",
      "activity": "14825",
      "session_id": "",
      "typeOption": "save_multiple_progress"
    },
    {
      "items": "4",
      "er": "0",
      "course": "573",
      "group": "3869",
      "unity": "579",
      "lesson": "630",
      "acpro": "2543",
      "typepro": "9",
      "pos": 0,
      "tini": "2025-04-20 07:59:48",
      "tlesson": "2025-04-20 08:03:53",
      "keyin": "",
      "activity": "14814",
      "session_id": "",
      "typeOption": "save_multiple_progress"
    },
    {
      "items": "4",
      "er": "0",
      "course": "573",
      "group": "3869",
      "unity": "579",
      "lesson": "630",
      "acpro": "2543",
      "typepro": "14",
      "pos": 0,
      "tini": "2025-04-20 07:59:48",
      "tlesson": "2025-04-20 08:03:53",
      "keyin": "",
      "activity": "14815",
      "session_id": "",
      "typeOption": "save_multiple_progress"
    },
    {
      "items": "4",
      "er": "0",
      "course": "573",
      "group": "3869",
      "unity": "579",
      "lesson": "630",
      "acpro": "2542",
      "typepro": "9",
      "pos": 0,
      "tini": "2025-04-20 07:59:48",
      "tlesson": "2025-04-20 08:03:53",
      "keyin": "",
      "activity": "14816",
      "session_id": "",
      "typeOption": "save_multiple_progress"
    },
    {
      "items": "4",
      "er": "0",
      "course": "573",
      "group": "3869",
      "unity": "579",
      "lesson": "630",
      "acpro": "2542",
      "typepro": "14",
      "pos": 0,
      "tini": "2025-04-20 07:59:48",
      "tlesson": "2025-04-20 08:03:53",
      "keyin": "",
      "activity": "14817",
      "session_id": "",
      "typeOption": "save_multiple_progress"
    },
    {
      "items": "4",
      "er": "0",
      "course": "573",
      "group": "3869",
      "unity": "579",
      "lesson": "630",
      "acpro": "2541",
      "typepro": "9",
      "pos": 0,
      "tini": "2025-04-20 07:59:48",
      "tlesson": "2025-04-20 08:03:53",
      "keyin": "",
      "activity": "14818",
      "session_id": "",
      "typeOption": "save_multiple_progress"
    },
    {
      "items": "4",
      "er": "0",
      "course": "573",
      "group": "3869",
      "unity": "579",
      "lesson": "630",
      "acpro": "2541",
      "typepro": "14",
      "pos": 0,
      "tini": "2025-04-20 07:59:48",
      "tlesson": "2025-04-20 08:03:53",
      "keyin": "",
      "activity": "14819",
      "session_id": "",
      "typeOption": "save_multiple_progress"
    },
    {
      "items": "4",
      "er": "0",
      "course": "573",
      "group": "3869",
      "unity": "579",
      "lesson": "630",
      "acpro": "2540",
      "typepro": "9",
      "pos": 0,
      "tini": "2025-04-20 07:59:48",
      "tlesson": "2025-04-20 08:03:53",
      "keyin": "",
      "activity": "14820",
      "session_id": "",
      "typeOption": "save_multiple_progress"
    },
    {
      "items": "4",
      "er": "0",
      "course": "573",
      "group": "3869",
      "unity": "579",
      "lesson": "630",
      "acpro": "2540",
      "typepro": "14",
      "pos": 0,
      "tini": "2025-04-20 07:59:48",
      "tlesson": "2025-04-20 08:03:53",
      "keyin": "",
      "activity": "14821",
      "session_id": "",
      "typeOption": "save_multiple_progress"
    },
    {
      "items": "4",
      "er": "0",
      "course": "573",
      "group": "3869",
      "unity": "579",
      "lesson": "630",
      "acpro": "2539",
      "typepro": "9",
      "pos": 0,
      "tini": "2025-04-20 07:59:48",
      "tlesson": "2025-04-20 08:03:53",
      "keyin": "",
      "activity": "14822",
      "session_id": "",
      "typeOption": "save_multiple_progress"
    },
    {
      "items": "4",
      "er": "0",
      "course": "573",
      "group": "3869",
      "unity": "579",
      "lesson": "630",
      "acpro": "2539",
      "typepro": "14",
      "pos": 0,
      "tini": "2025-04-20 07:59:48",
      "tlesson": "2025-04-20 08:03:53",
      "keyin": "",
      "activity": "14823",
      "session_id": "",
      "typeOption": "save_multiple_progress"
    },
    {
      "items": "4",
      "er": "0",
      "course": "573",
      "group": "3869",
      "unity": "579",
      "lesson": "630",
      "acpro": "2538",
      "typepro": "9",
      "pos": 0,
      "tini": "2025-04-20 07:59:48",
      "tlesson": "2025-04-20 08:03:53",
      "keyin": "",
      "activity": "14824",
      "session_id": "",
      "typeOption": "save_multiple_progress"
    },
    {
      "items": "1",
      "er": "0",
      "course": "573",
      "group": "3869",
      "unity": "579",
      "lesson": "630",
      "acpro": "2687",
      "typepro": "20",
      "pos": 0,
      "tini": "2025-04-20 07:59:48",
      "tlesson": "2025-04-20 08:03:53",
      "keyin": "",
      "activity": "14812",
      "session_id": "",
      "typeOption": "save_multiple_progress"
    },
    {
      "items": "3",
      "er": "0",
      "course": "573",
      "group": "3869",
      "unity": "579",
      "lesson": "630",
      "acpro": "2688",
      "typepro": "20",
      "pos": 0,
      "tini": "2025-04-20 07:59:48",
      "tlesson": "2025-04-20 08:03:53",
      "keyin": "",
      "activity": "14811",
      "session_id": "",
      "typeOption": "save_multiple_progress"
    },
    {
      "items": "3",
      "er": "0",
      "course": "573",
      "group": "3869",
      "unity": "579",
      "lesson": "630",
      "acpro": "2689",
      "typepro": "20",
      "pos": 0,
      "tini": "2025-04-20 07:59:48",
      "tlesson": "2025-04-20 08:03:53",
      "keyin": "",
      "activity": "14810",
      "session_id": "",
      "typeOption": "save_multiple_progress"
    },
    {
      "items": "3",
      "er": "0",
      "course": "573",
      "group": "3869",
      "unity": "579",
      "lesson": "630",
      "acpro": "2690",
      "typepro": "20",
      "pos": 0,
      "tini": "2025-04-20 07:59:48",
      "tlesson": "2025-04-20 08:03:53",
      "keyin": "",
      "activity": "14809",
      "session_id": "",
      "typeOption": "save_multiple_progress"
    },
    {
      "items": "3",
      "er": "0",
      "course": "573",
      "group": "3869",
      "unity": "579",
      "lesson": "630",
      "acpro": "2691",
      "typepro": "20",
      "pos": 0,
      "tini": "2025-04-20 07:59:48",
      "tlesson": "2025-04-20 08:03:53",
      "keyin": "",
      "activity": "14808",
      "session_id": "",
      "typeOption": "save_multiple_progress"
    },
    {
      "items": "3",
      "er": "0",
      "course": "573",
      "group": "3869",
      "unity": "579",
      "lesson": "630",
      "acpro": "2692",
      "typepro": "20",
      "pos": 0,
      "tini": "2025-04-20 07:59:48",
      "tlesson": "2025-04-20 08:03:53",
      "keyin": "",
      "activity": "14807",
      "session_id": "",
      "typeOption": "save_multiple_progress"
    },
    {
      "items": "3",
      "er": "0",
      "course": "573",
      "group": "3869",
      "unity": "579",
      "lesson": "630",
      "acpro": "2693",
      "typepro": "20",
      "pos": 0,
      "tini": "2025-04-20 07:59:48",
      "tlesson": "2025-04-20 08:03:53",
      "keyin": "",
      "activity": "14806",
      "session_id": "",
      "typeOption": "save_multiple_progress"
    },
    {
      "items": "3",
      "er": "0",
      "course": "573",
      "group": "3869",
      "unity": "579",
      "lesson": "630",
      "acpro": "2695",
      "typepro": "20",
      "pos": 0,
      "tini": "2025-04-20 07:59:48",
      "tlesson": "2025-04-20 08:03:53",
      "keyin": "",
      "activity": "14805",
      "session_id": "",
      "typeOption": "save_multiple_progress"
    },
    {
      "items": "3",
      "er": "0",
      "course": "573",
      "group": "3869",
      "unity": "579",
      "lesson": "630",
      "acpro": "2696",
      "typepro": "20",
      "pos": 0,
      "tini": "2025-04-20 07:59:48",
      "tlesson": "2025-04-20 08:03:53",
      "keyin": "",
      "activity": "14804",
      "session_id": "",
      "typeOption": "save_multiple_progress"
    },
    {
      "items": "3",
      "er": "0",
      "course": "573",
      "group": "3869",
      "unity": "579",
      "lesson": "630",
      "acpro": "2697",
      "typepro": "20",
      "pos": 0,
      "tini": "2025-04-20 07:59:48",
      "tlesson": "2025-04-20 08:03:53",
      "keyin": "",
      "activity": "14803",
      "session_id": "",
      "typeOption": "save_multiple_progress"
    },
    {
      "items": "3",
      "er": "0",
      "course": "573",
      "group": "3869",
      "unity": "579",
      "lesson": "630",
      "acpro": "2698",
      "typepro": "20",
      "pos": 0,
      "tini": "2025-04-20 07:59:48",
      "tlesson": "2025-04-20 08:03:53",
      "keyin": "",
      "activity": "14802",
      "session_id": "",
      "typeOption": "save_multiple_progress"
    },
    {
      "items": "3",
      "er": "0",
      "course": "573",
      "group": "3869",
      "unity": "579",
      "lesson": "630",
      "acpro": "2699",
      "typepro": "20",
      "pos": 0,
      "tini": "2025-04-20 07:59:48",
      "tlesson": "2025-04-20 08:03:53",
      "keyin": "",
      "activity": "14801",
      "session_id": "",
      "typeOption": "save_multiple_progress"
    },
    {
      "items": "3",
      "er": "0",
      "course": "573",
      "group": "3869",
      "unity": "579",
      "lesson": "630",
      "acpro": "2701",
      "typepro": "20",
      "pos": 0,
      "tini": "2025-04-20 07:59:48",
      "tlesson": "2025-04-20 08:03:53",
      "keyin": "",
      "activity": "14800",
      "session_id": "",
      "typeOption": "save_multiple_progress"
    },
    {
      "items": "3",
      "er": "0",
      "course": "573",
      "group": "3869",
      "unity": "579",
      "lesson": "630",
      "acpro": "2702",
      "typepro": "20",
      "pos": 0,
      "tini": "2025-04-20 07:59:48",
      "tlesson": "2025-04-20 08:03:53",
      "keyin": "",
      "activity": "14799",
      "session_id": "",
      "typeOption": "save_multiple_progress"
    }
  ],
  "dataV2": {
    "group": "3869",
    "course": "573",
    "unity": "579",
    "lesson": "630",
    "array_activitys": [
      {
        "total": "4",
        "errors": 0,
        "success": "4",
        "type": "14",
        "activity": "14825"
      },
      {
        "total": "4",
        "errors": 0,
        "success": "4",
        "type": "9",
        "activity": "14814"
      },
      {
        "total": "4",
        "errors": 0,
        "success": "4",
        "type": "14",
        "activity": "14815"
      },
      {
        "total": "4",
        "errors": 0,
        "success": "4",
        "type": "9",
        "activity": "14816"
      },
      {
        "total": "4",
        "errors": 0,
        "success": "4",
        "type": "14",
        "activity": "14817"
      },
      {
        "total": "4",
        "errors": 0,
        "success": "4",
        "type": "9",
        "activity": "14818"
      },
      {
        "total": "4",
        "errors": 0,
        "success": "4",
        "type": "14",
        "activity": "14819"
      },
      {
        "total": "4",
        "errors": 0,
        "success": "4",
        "type": "9",
        "activity": "14820"
      },
      {
        "total": "4",
        "errors": 0,
        "success": "4",
        "type": "14",
        "activity": "14821"
      },
      {
        "total": "4",
        "errors": 0,
        "success": "4",
        "type": "9",
        "activity": "14822"
      },
      {
        "total": "4",
        "errors": 0,
        "success": "4",
        "type": "14",
        "activity": "14823"
      },
      {
        "total": "4",
        "errors": 0,
        "success": "4",
        "type": "9",
        "activity": "14824"
      },
      {
        "total": "1",
        "errors": 0,
        "success": "1",
        "type": "20",
        "activity": "14812"
      },
      {
        "total": "3",
        "errors": 0,
        "success": "3",
        "type": "20",
        "activity": "14811"
      },
      {
        "total": "3",
        "errors": 0,
        "success": "3",
        "type": "20",
        "activity": "14810"
      },
      {
        "total": "3",
        "errors": 0,
        "success": "3",
        "type": "20",
        "activity": "14809"
      },
      {
        "total": "3",
        "errors": 0,
        "success": "3",
        "type": "20",
        "activity": "14808"
      },
      {
        "total": "3",
        "errors": 0,
        "success": "3",
        "type": "20",
        "activity": "14807"
      },
      {
        "total": "3",
        "errors": 0,
        "success": "3",
        "type": "20",
        "activity": "14806"
      },
      {
        "total": "3",
        "errors": 0,
        "success": "3",
        "type": "20",
        "activity": "14805"
      },
      {
        "total": "3",
        "errors": 0,
        "success": "3",
        "type": "20",
        "activity": "14804"
      },
      {
        "total": "3",
        "errors": 0,
        "success": "3",
        "type": "20",
        "activity": "14803"
      },
      {
        "total": "3",
        "errors": 0,
        "success": "3",
        "type": "20",
        "activity": "14802"
      },
      {
        "total": "3",
        "errors": 0,
        "success": "3",
        "type": "20",
        "activity": "14801"
      },
      {
        "total": "3",
        "errors": 0,
        "success": "3",
        "type": "20",
        "activity": "14800"
      },
      {
        "total": "3",
        "errors": 0,
        "success": "3",
        "type": "20",
        "activity": "14799"
      }
    ],
    "total_activitys": 88,
    "errors_result_activitys": 0,
    "success_result_activitys": 88,
    "pending_result_activitys": 0,
    "total_groups_activitys": 26,
    "total_groups_activitys_success": 26,
    "total_groups_activitys_pendings": 0,
    "success_lesson_date": "",
    "success_lesson_activities": 2,
    "year": "2025"
  },
  "typeOption": "save_multiple_progress_webv2"
}