{
  "data": [
    {
      "items": "1",
      "er": "0",
      "course": "559",
      "group": "3777",
      "unity": "572",
      "lesson": "590",
      "acpro": "3181",
      "typepro": "20",
      "pos": 0,
      "tini": "2025-04-20 07:59:48",
      "tlesson": "2025-04-20 08:03:53",
      "keyin": "",
      "activity": "12837",
      "session_id": "",
      "typeOption": "save_multiple_progress"
    },
    {
      "items": "4",
      "er": "0",
      "course": "559",
      "group": "3777",
      "unity": "572",
      "lesson": "590",
      "acpro": "442",
      "typepro": "9",
      "pos": 0,
      "tini": "2025-04-20 07:59:48",
      "tlesson": "2025-04-20 08:03:53",
      "keyin": "",
      "activity": "12819",
      "session_id": "",
      "typeOption": "save_multiple_progress"
    },
    {
      "items": "2",
      "er": "0",
      "course": "559",
      "group": "3777",
      "unity": "572",
      "lesson": "590",
      "acpro": "450",
      "typepro": "9",
      "pos": 0,
      "tini": "2025-04-20 07:59:48",
      "tlesson": "2025-04-20 08:03:53",
      "keyin": "",
      "activity": "12835",
      "session_id": "",
      "typeOption": "save_multiple_progress"
    },
    {
      "items": "2",
      "er": "0",
      "course": "559",
      "group": "3777",
      "unity": "572",
      "lesson": "590",
      "acpro": "449",
      "typepro": "9",
      "pos": 0,
      "tini": "2025-04-20 07:59:48",
      "tlesson": "2025-04-20 08:03:53",
      "keyin": "",
      "activity": "12833",
      "session_id": "",
      "typeOption": "save_multiple_progress"
    },
    {
      "items": "2",
      "er": "0",
      "course": "559",
      "group": "3777",
      "unity": "572",
      "lesson": "590",
      "acpro": "447",
      "typepro": "9",
      "pos": 0,
      "tini": "2025-04-20 07:59:48",
      "tlesson": "2025-04-20 08:03:53",
      "keyin": "",
      "activity": "12831",
      "session_id": "",
      "typeOption": "save_multiple_progress"
    },
    {
      "items": "2",
      "er": "0",
      "course": "559",
      "group": "3777",
      "unity": "572",
      "lesson": "590",
      "acpro": "446",
      "typepro": "9",
      "pos": 0,
      "tini": "2025-04-20 07:59:48",
      "tlesson": "2025-04-20 08:03:53",
      "keyin": "",
      "activity": "12829",
      "session_id": "",
      "typeOption": "save_multiple_progress"
    },
    {
      "items": "2",
      "er": "0",
      "course": "559",
      "group": "3777",
      "unity": "572",
      "lesson": "590",
      "acpro": "445",
      "typepro": "9",
      "pos": 0,
      "tini": "2025-04-20 07:59:48",
      "tlesson": "2025-04-20 08:03:53",
      "keyin": "",
      "activity": "12827",
      "session_id": "",
      "typeOption": "save_multiple_progress"
    },
    {
      "items": "4",
      "er": "0",
      "course": "559",
      "group": "3777",
      "unity": "572",
      "lesson": "590",
      "acpro": "442",
      "typepro": "21",
      "pos": 0,
      "tini": "2025-04-20 07:59:48",
      "tlesson": "2025-04-20 08:03:53",
      "keyin": "",
      "activity": "12822",
      "session_id": "",
      "typeOption": "save_multiple_progress"
    },
    {
      "items": "4",
      "er": "0",
      "course": "559",
      "group": "3777",
      "unity": "572",
      "lesson": "590",
      "acpro": "442",
      "typepro": "18",
      "pos": 0,
      "tini": "2025-04-20 07:59:48",
      "tlesson": "2025-04-20 08:03:53",
      "keyin": "",
      "activity": "12821",
      "session_id": "",
      "typeOption": "save_multiple_progress"
    },
    {
      "items": "4",
      "er": "0",
      "course": "559",
      "group": "3777",
      "unity": "572",
      "lesson": "590",
      "acpro": "442",
      "typepro": "10",
      "pos": 0,
      "tini": "2025-04-20 07:59:48",
      "tlesson": "2025-04-20 08:03:53",
      "keyin": "",
      "activity": "12820",
      "session_id": "",
      "typeOption": "save_multiple_progress"
    },
    {
      "items": "2",
      "er": "0",
      "course": "559",
      "group": "3777",
      "unity": "572",
      "lesson": "590",
      "acpro": "450",
      "typepro": "14",
      "pos": 0,
      "tini": "2025-04-20 07:59:48",
      "tlesson": "2025-04-20 08:03:53",
      "keyin": "",
      "activity": "12836",
      "session_id": "",
      "typeOption": "save_multiple_progress"
    },
    {
      "items": "2",
      "er": "0",
      "course": "559",
      "group": "3777",
      "unity": "572",
      "lesson": "590",
      "acpro": "449",
      "typepro": "14",
      "pos": 0,
      "tini": "2025-04-20 07:59:48",
      "tlesson": "2025-04-20 08:03:53",
      "keyin": "",
      "activity": "12834",
      "session_id": "",
      "typeOption": "save_multiple_progress"
    },
    {
      "items": "2",
      "er": "0",
      "course": "559",
      "group": "3777",
      "unity": "572",
      "lesson": "590",
      "acpro": "447",
      "typepro": "14",
      "pos": 0,
      "tini": "2025-04-20 07:59:48",
      "tlesson": "2025-04-20 08:03:53",
      "keyin": "",
      "activity": "12832",
      "session_id": "",
      "typeOption": "save_multiple_progress"
    },
    {
      "items": "2",
      "er": "0",
      "course": "559",
      "group": "3777",
      "unity": "572",
      "lesson": "590",
      "acpro": "446",
      "typepro": "14",
      "pos": 0,
      "tini": "2025-04-20 07:59:48",
      "tlesson": "2025-04-20 08:03:53",
      "keyin": "",
      "activity": "12830",
      "session_id": "",
      "typeOption": "save_multiple_progress"
    },
    {
      "items": "2",
      "er": "0",
      "course": "559",
      "group": "3777",
      "unity": "572",
      "lesson": "590",
      "acpro": "445",
      "typepro": "14",
      "pos": 0,
      "tini": "2025-04-20 07:59:48",
      "tlesson": "2025-04-20 08:03:53",
      "keyin": "",
      "activity": "12828",
      "session_id": "",
      "typeOption": "save_multiple_progress"
    },
    {
      "items": "4",
      "er": "0",
      "course": "559",
      "group": "3777",
      "unity": "572",
      "lesson": "590",
      "acpro": "427",
      "typepro": "20",
      "pos": 0,
      "tini": "2025-04-20 07:59:48",
      "tlesson": "2025-04-20 08:03:53",
      "keyin": "",
      "activity": "12847",
      "session_id": "",
      "typeOption": "save_multiple_progress"
    },
    {
      "items": "2",
      "er": "0",
      "course": "559",
      "group": "3777",
      "unity": "572",
      "lesson": "590",
      "acpro": "426",
      "typepro": "20",
      "pos": 0,
      "tini": "2025-04-20 07:59:48",
      "tlesson": "2025-04-20 08:03:53",
      "keyin": "",
      "activity": "12846",
      "session_id": "",
      "typeOption": "save_multiple_progress"
    },
    {
      "items": "2",
      "er": "0",
      "course": "559",
      "group": "3777",
      "unity": "572",
      "lesson": "590",
      "acpro": "422",
      "typepro": "20",
      "pos": 0,
      "tini": "2025-04-20 07:59:48",
      "tlesson": "2025-04-20 08:03:53",
      "keyin": "",
      "activity": "12845",
      "session_id": "",
      "typeOption": "save_multiple_progress"
    },
    {
      "items": "2",
      "er": "0",
      "course": "559",
      "group": "3777",
      "unity": "572",
      "lesson": "590",
      "acpro": "431",
      "typepro": "20",
      "pos": 0,
      "tini": "2025-04-20 07:59:48",
      "tlesson": "2025-04-20 08:03:53",
      "keyin": "",
      "activity": "12844",
      "session_id": "",
      "typeOption": "save_multiple_progress"
    },
    {
      "items": "3",
      "er": "0",
      "course": "559",
      "group": "3777",
      "unity": "572",
      "lesson": "590",
      "acpro": "451",
      "typepro": "20",
      "pos": 0,
      "tini": "2025-04-20 07:59:48",
      "tlesson": "2025-04-20 08:03:53",
      "keyin": "",
      "activity": "12843",
      "session_id": "",
      "typeOption": "save_multiple_progress"
    },
    {
      "items": "2",
      "er": "0",
      "course": "559",
      "group": "3777",
      "unity": "572",
      "lesson": "590",
      "acpro": "435",
      "typepro": "20",
      "pos": 0,
      "tini": "2025-04-20 07:59:48",
      "tlesson": "2025-04-20 08:03:53",
      "keyin": "",
      "activity": "12842",
      "session_id": "",
      "typeOption": "save_multiple_progress"
    },
    {
      "items": "2",
      "er": "0",
      "course": "559",
      "group": "3777",
      "unity": "572",
      "lesson": "590",
      "acpro": "428",
      "typepro": "20",
      "pos": 0,
      "tini": "2025-04-20 07:59:48",
      "tlesson": "2025-04-20 08:03:53",
      "keyin": "",
      "activity": "12840",
      "session_id": "",
      "typeOption": "save_multiple_progress"
    },
    {
      "items": "2",
      "er": "0",
      "course": "559",
      "group": "3777",
      "unity": "572",
      "lesson": "590",
      "acpro": "432",
      "typepro": "20",
      "pos": 0,
      "tini": "2025-04-20 07:59:48",
      "tlesson": "2025-04-20 08:03:53",
      "keyin": "",
      "activity": "12839",
      "session_id": "",
      "typeOption": "save_multiple_progress"
    },
    {
      "items": "2",
      "er": "0",
      "course": "559",
      "group": "3777",
      "unity": "572",
      "lesson": "590",
      "acpro": "423",
      "typepro": "20",
      "pos": 0,
      "tini": "2025-04-20 07:59:48",
      "tlesson": "2025-04-20 08:03:53",
      "keyin": "",
      "activity": "12841",
      "session_id": "",
      "typeOption": "save_multiple_progress"
    },
    {
      "items": "2",
      "er": "0",
      "course": "559",
      "group": "3777",
      "unity": "572",
      "lesson": "590",
      "acpro": "436",
      "typepro": "20",
      "pos": 0,
      "tini": "2025-04-20 07:59:48",
      "tlesson": "2025-04-20 08:03:53",
      "keyin": "",
      "activity": "12838",
      "session_id": "",
      "typeOption": "save_multiple_progress"
    },
    {
      "items": "2",
      "er": "0",
      "course": "559",
      "group": "3777",
      "unity": "572",
      "lesson": "590",
      "acpro": "429",
      "typepro": "20",
      "pos": 0,
      "tini": "2025-04-20 07:59:48",
      "tlesson": "2025-04-20 08:03:53",
      "keyin": "",
      "activity": "12848",
      "session_id": "",
      "typeOption": "save_multiple_progress"
    }
  ],
  "dataV2": {
    "group": "3777",
    "course": "559",
    "unity": "572",
    "lesson": "590",
    "array_activitys": [
      {
        "total": "1",
        "errors": 0,
        "success": "1",
        "type": "20",
        "activity": "12837"
      },
      {
        "total": "4",
        "errors": 0,
        "success": "4",
        "type": "9",
        "activity": "12819"
      },
      {
        "total": "2",
        "errors": 0,
        "success": "2",
        "type": "9",
        "activity": "12835"
      },
      {
        "total": "2",
        "errors": 0,
        "success": "2",
        "type": "9",
        "activity": "12833"
      },
      {
        "total": "2",
        "errors": 0,
        "success": "2",
        "type": "9",
        "activity": "12831"
      },
      {
        "total": "2",
        "errors": 0,
        "success": "2",
        "type": "9",
        "activity": "12829"
      },
      {
        "total": "2",
        "errors": 0,
        "success": "2",
        "type": "9",
        "activity": "12827"
      },
      {
        "total": "4",
        "errors": 0,
        "success": "4",
        "type": "21",
        "activity": "12822"
      },
      {
        "total": "4",
        "errors": 0,
        "success": "4",
        "type": "18",
        "activity": "12821"
      },
      {
        "total": "4",
        "errors": 0,
        "success": "4",
        "type": "10",
        "activity": "12820"
      },
      {
        "total": "2",
        "errors": 0,
        "success": "2",
        "type": "14",
        "activity": "12836"
      },
      {
        "total": "2",
        "errors": 0,
        "success": "2",
        "type": "14",
        "activity": "12834"
      },
      {
        "total": "2",
        "errors": 0,
        "success": "2",
        "type": "14",
        "activity": "12832"
      },
      {
        "total": "2",
        "errors": 0,
        "success": "2",
        "type": "14",
        "activity": "12830"
      },
      {
        "total": "2",
        "errors": 0,
        "success": "2",
        "type": "14",
        "activity": "12828"
      },
      {
        "total": "4",
        "errors": 0,
        "success": "4",
        "type": "20",
        "activity": "12847"
      },
      {
        "total": "2",
        "errors": 0,
        "success": "2",
        "type": "20",
        "activity": "12846"
      },
      {
        "total": "2",
        "errors": 0,
        "success": "2",
        "type": "20",
        "activity": "12845"
      },
      {
        "total": "2",
        "errors": 0,
        "success": "2",
        "type": "20",
        "activity": "12844"
      },
      {
        "total": "3",
        "errors": 0,
        "success": "3",
        "type": "20",
        "activity": "12843"
      },
      {
        "total": "2",
        "errors": 0,
        "success": "2",
        "type": "20",
        "activity": "12842"
      },
      {
        "total": "2",
        "errors": 0,
        "success": "2",
        "type": "20",
        "activity": "12840"
      },
      {
        "total": "2",
        "errors": 0,
        "success": "2",
        "type": "20",
        "activity": "12839"
      },
      {
        "total": "2",
        "errors": 0,
        "success": "2",
        "type": "20",
        "activity": "12841"
      },
      {
        "total": "2",
        "errors": 0,
        "success": "2",
        "type": "20",
        "activity": "12838"
      },
      {
        "total": "2",
        "errors": 0,
        "success": "2",
        "type": "20",
        "activity": "12848"
      }
    ],
    "total_activitys": 62,
    "errors_result_activitys": 0,
    "success_result_activitys": 62,
    "pending_result_activitys": 0,
    "total_groups_activitys": 26,
    "total_groups_activitys_success": 26,
    "total_groups_activitys_pendings": 0,
    "success_lesson_date": "",
    "success_lesson_activities": 1,
    "year": "2025"
  },
  "typeOption": "save_multiple_progress_webv2"
}